setup.py
WintxDriver_MySQL.egg-info/PKG-INFO
WintxDriver_MySQL.egg-info/SOURCES.txt
WintxDriver_MySQL.egg-info/dependency_links.txt
WintxDriver_MySQL.egg-info/namespace_packages.txt
WintxDriver_MySQL.egg-info/requires.txt
WintxDriver_MySQL.egg-info/top_level.txt
wintx/__init__.py
wintx/drivers/__init__.py
wintx/drivers/MySQL/Config.py
wintx/drivers/MySQL/Driver.py
wintx/drivers/MySQL/MySQLError.py
wintx/drivers/MySQL/__init__.py